README.rst
setup.py
django_modify_history.egg-info/PKG-INFO
django_modify_history.egg-info/SOURCES.txt
django_modify_history.egg-info/dependency_links.txt
django_modify_history.egg-info/requires.txt
django_modify_history.egg-info/top_level.txt
django_modify_history.egg-info/zip-safe
modify_history/__init__.py
modify_history/admin.py
modify_history/exceptions.py
modify_history/feeds.py
modify_history/models.py
modify_history/sites.py
modify_history/urls.py
modify_history/backends/__init__.py
modify_history/backends/base.py
modify_history/backends/basic.py
modify_history/backends/comment.py
modify_history/templatetags/__init__.py
modify_history/templatetags/historytags.py