Metadata-Version: 1.0
Name: django-modify-history
Version: 0.1rc2
Summary: Automatically create history database when perticular model is saved.
Home-page: https://github.com/lambdalisue/django-modify-history
Author: Alisue
Author-email: lambdalisue@hashnote.net
License: BSD
Download-URL: https://github.com/lambdalisue/django-modify-history/tarball/master
Keywords: django history modify
Platform: UNKNOWN
Classifier: Framework :: Django
Classifier: Intended Audience :: Developers
Classifier: License :: OSI Approved :: BSD License
Classifier: Programming Language :: Python
Classifier: Topic :: Internet :: WWW/HTTP
